type_check/__init__.py
type_check/__private__.py
type_check/builtin_checks.py
type_check/core.py
type_check/primitives.py
type_check/proxy.py
type_check/transparent.py
rttc-1.0.6.dist-info/LICENSE
rttc-1.0.6.dist-info/METADATA
rttc-1.0.6.dist-info/WHEEL
rttc-1.0.6.dist-info/top_level.txt
rttc-1.0.6.dist-info/RECORD
