Metadata-Version: 2.1
Name: rttc
Version: 1.0.6
Summary: Python run-time type check
Keywords: type check safe
Classifier: License :: OSI Approved :: MIT License
Classifier: Programming Language :: Python :: 3.10
Classifier: Programming Language :: Python :: 3.11
Classifier: Programming Language :: Python :: 3.12
Classifier: Programming Language :: Python :: 3.13
License-File: LICENSE
